model_tuner/__init__.py
model_tuner/bootstrapper.py
model_tuner/logo.py
model_tuner/main.py
model_tuner/model_tuner_utils.py
model_tuner/pickleObjects.py
model_tuner/threshold_optimization.py
model_tuner-0.0.34b3.dist-info/licenses/LICENSE.md
model_tuner-0.0.34b3.dist-info/METADATA
model_tuner-0.0.34b3.dist-info/WHEEL
model_tuner-0.0.34b3.dist-info/top_level.txt
model_tuner-0.0.34b3.dist-info/RECORD
