Metadata-Version: 2.4
Name: model_tuner
Version: 0.0.34b3
Summary: A Python library for training and tuning machine learning models.
Author-email: "UCLA CTSI ML Team: Arthur Funnell, Leonid Shpaner, Panayiotis Petousis" <pp89@ucla.edu>
Project-URL: Author Website, https://www.mii.ucla.edu/
Project-URL: Documentation, https://uclamii.github.io/model_tuner
Project-URL: Zenodo Archive, https://zenodo.org/doi/10.5281/zenodo.12727322
Project-URL: Source Code, https://github.com/uclamii/model_tuner/
Classifier: Programming Language :: Python :: 3
Classifier: Operating System :: OS Independent
Requires-Python: >=3.7
License-File: LICENSE.md
Requires-Dist: joblib==1.3.2
Requires-Dist: tqdm==4.66.4
Requires-Dist: catboost==1.2.7
Requires-Dist: numpy<1.23.0,>=1.21.4; python_version >= "3.7" and python_version < "3.8"
Requires-Dist: pandas<1.3.5,>=1.1.5; python_version >= "3.7" and python_version < "3.8"
Requires-Dist: scikit-learn<1.0.2,>=0.23.2; python_version >= "3.7" and python_version < "3.8"
Requires-Dist: scipy<1.11,>=1.4.1; python_version >= "3.7" and python_version < "3.8"
Requires-Dist: imbalanced-learn<0.8.0,>=0.7.0; python_version >= "3.7" and python_version < "3.8"
Requires-Dist: scikit-optimize<0.10.2,>=0.8.1; python_version >= "3.7" and python_version < "3.8"
Requires-Dist: xgboost<2.1.2,>=1.6.2; python_version >= "3.7" and python_version < "3.8"
Requires-Dist: setuptools==75.1.0; python_version == "3.8"
Requires-Dist: wheel==0.44.0; python_version == "3.8"
Requires-Dist: numpy<2.0.0,>=1.19.5; python_version == "3.8"
Requires-Dist: pandas<2.2.3,>=1.3.5; python_version == "3.8"
Requires-Dist: scikit-learn<1.4.0,>=1.0.2; python_version == "3.8"
Requires-Dist: scipy<1.11,>=1.6.3; python_version == "3.8"
Requires-Dist: scikit-optimize==0.10.2; python_version == "3.8"
Requires-Dist: imbalanced-learn==0.12.4; python_version == "3.8"
Requires-Dist: xgboost==2.1.2; python_version == "3.8"
Requires-Dist: setuptools==75.1.0; python_version >= "3.9" and python_version < "3.11"
Requires-Dist: wheel==0.44.0; python_version >= "3.9" and python_version < "3.11"
Requires-Dist: numpy<2.0.0,>=1.19.5; python_version >= "3.9" and python_version < "3.11"
Requires-Dist: pandas<2.2.3,>=1.3.5; python_version >= "3.9" and python_version < "3.11"
Requires-Dist: scikit-learn<=1.5.1,>=1.0.2; python_version >= "3.9" and python_version < "3.11"
Requires-Dist: scipy<=1.14.0,>=1.6.3; python_version >= "3.9" and python_version < "3.11"
Requires-Dist: scikit-optimize==0.10.2; python_version >= "3.9" and python_version < "3.11"
Requires-Dist: imbalanced-learn==0.12.4; python_version >= "3.9" and python_version < "3.11"
Requires-Dist: xgboost==2.1.2; python_version >= "3.9" and python_version < "3.11"
Requires-Dist: setuptools==75.1.0; python_version >= "3.11"
Requires-Dist: wheel==0.44.0; python_version >= "3.11"
Requires-Dist: numpy<2.0.0,>=1.19.5; python_version >= "3.11"
Requires-Dist: pandas<2.2.3,>=1.3.5; python_version >= "3.11"
Requires-Dist: scikit-learn==1.5.1; python_version >= "3.11"
Requires-Dist: scipy==1.14.0; python_version >= "3.11"
Requires-Dist: imbalanced-learn==0.12.4; python_version >= "3.11"
Requires-Dist: scikit-optimize==0.10.2; python_version >= "3.11"
Requires-Dist: xgboost==2.1.2; python_version >= "3.11"
Dynamic: license-file
